colortools/__init__.py
colortools/__main__.py
colortools/analysis.py
colortools/analyzed_image.py
colortools/cli.py
colortools/config.py
colortools/heuristics.py
colortools/sort.py
colortools/util.py
colortools/visualization.py
nbp_colortools-1.0.1.dist-info/LICENSE
nbp_colortools-1.0.1.dist-info/METADATA
nbp_colortools-1.0.1.dist-info/WHEEL
nbp_colortools-1.0.1.dist-info/entry_points.txt
nbp_colortools-1.0.1.dist-info/top_level.txt
nbp_colortools-1.0.1.dist-info/RECORD
