Metadata-Version: 2.1
Name: nbp-colortools
Version: 1.0.1
Summary: A collection of tools for analyzing and sorting images by color.
Home-page: https://github.com/nbeckerphoto/colortools
Author: Nick Becker
Author-email: nbeckerphoto@gmail.com
Keywords: color analysis,image analysis,photography
Classifier: Development Status :: 4 - Beta
Classifier: License :: OSI Approved :: MIT License
Classifier: Environment :: Console
Classifier: Programming Language :: Python :: 3
Classifier: Topic :: Scientific/Engineering :: Image Processing
Classifier: Topic :: Software Development :: Libraries
Requires-Python: >=3.9
License-File: LICENSE
Requires-Dist: pillow (>=9.2.0)
Requires-Dist: scikit-learn (>=1.1.1)
Requires-Dist: numpy (>=1.23.1)
Requires-Dist: tqdm
